LICENSE
MANIFEST.in
README.md
requirements.txt
setup.py
pytest_crontab/__init__.py
pytest_crontab/plugin.py
pytest_crontab.egg-info/PKG-INFO
pytest_crontab.egg-info/SOURCES.txt
pytest_crontab.egg-info/dependency_links.txt
pytest_crontab.egg-info/entry_points.txt
pytest_crontab.egg-info/requires.txt
pytest_crontab.egg-info/top_level.txt
pytest_crontab.egg-info/zip-safe